mylibrary/__init__.py
mylibrary/veicolo.py
mylibrary_wtitze-0.1.dist-info/METADATA
mylibrary_wtitze-0.1.dist-info/WHEEL
mylibrary_wtitze-0.1.dist-info/top_level.txt
mylibrary_wtitze-0.1.dist-info/RECORD
