Metadata-Version: 2.1
Name: mylibrary-wtitze
Version: 0.1
Summary: Una libreria per gestire veicoli in Python
Home-page: https://github.com/wtitze/mylibrary
Author: Tuo Nome
Classifier: Programming Language :: Python :: 3
Classifier: License :: OSI Approved :: MIT License
Classifier: Operating System :: OS Independent
Requires-Python: >=3.6
